offprem/__init__.py
offprem/__main__.py
offprem/environments.py
offprem/exceptions.py
offprem/offprem.py
offprem-0.0.2b0.dist-info/LICENSE
offprem-0.0.2b0.dist-info/METADATA
offprem-0.0.2b0.dist-info/WHEEL
offprem-0.0.2b0.dist-info/top_level.txt
offprem-0.0.2b0.dist-info/RECORD
