Metadata-Version: 2.1
Name: offprem
Version: 0.0.2b0
Summary: A tool to interact with VPCs configured in AWS accounts and roles.
Home-page: https://github.com/Fauxsys/offprem
Author: Steven Cassamajor
Author-email: contributor@networkaxis.org
License: UNKNOWN
Platform: UNKNOWN
Classifier: Programming Language :: Python :: 3 :: Only
Classifier: Intended Audience :: System Administrators
Classifier: Topic :: System :: Distributed Computing
Classifier: License :: OSI Approved :: MIT License
Requires-Python: >=3.9
License-File: LICENSE
Requires-Dist: boto3
Requires-Dist: parserconfig
Provides-Extra: test
Requires-Dist: pytest ; extra == 'test'
Requires-Dist: pytest-cov ; extra == 'test'
Requires-Dist: tox ; extra == 'test'
